SerilizerGrishchuk
