Metadata-Version: 2.1
Name: SerilizerGrishchuk
Version: 0.1.2
Summary: Demo library
Home-page: UNKNOWN
Author: Grishchuk Alexandr
Author-email: grishchuk.2004ag@gmail.com
License: UNKNOWN
Platform: UNKNOWN
Classifier: Intended Audience :: Developers
Classifier: License :: OSI Approved :: MIT License
Classifier: Programming Language :: Python
Classifier: Programming Language :: Python :: 3
Classifier: Programming Language :: Python :: 3.6
Classifier: Programming Language :: Python :: 3.7
Classifier: Programming Language :: Python :: 3.8
Classifier: Programming Language :: Python :: 3.9
Classifier: Operating System :: OS Independent
